setup.cfg
setup.py
skipper/__init__.py
skipper/cli.py
skipper/conf.py
skipper/creds.py
skipper/exceptions.py
skipper/fleet.py
skipper/formatter.py
skipper/hosts.py
skipper/instances.py
skipper/logger.py
skipper/ports.py
skipper/project.py
skipper/services.py
skipper/ssh.py
skipper/utils.py
skipper.egg-info/PKG-INFO
skipper.egg-info/SOURCES.txt
skipper.egg-info/dependency_links.txt
skipper.egg-info/entry_points.txt
skipper.egg-info/requires.txt
skipper.egg-info/top_level.txt
skipper/aws/__init__.py
skipper/aws/ec2.py
skipper/aws/groups.py
skipper/aws/helpers.py
skipper/aws/host.py
skipper/aws/instances.py
skipper/aws/regions.py
skipper/aws/sizes.py