Metadata-Version: 1.0
Name: skipper
Version: 0.0.1
Summary: Build, deploy and orchestrate your application using Docker.
Home-page: https://github.com/cameronmaske/skipper
Author: Cameron Maske
Author-email: cameronmaske@gmail.com
License: BSD
Keywords: docker,paas,coreos
Platform: UNKNOWN
